{"gliders":[ {"glider":"206 Hornet" , "glider_and_max_pilot_wgt":318, "max_ballast":100, "V1":80,"W1":-0.606, "V2":120, "W2":-0.99, "V3":160, "W3":-1.918, "wing_area":9.8, "ballast_dump_time":41.666, "handicap":100, "glider_empty_mass":227, "pilotMass":91, "a":-0.00017, "b":0.0244, "c":-1.47, "minSinkSpeed":72, "minSinkRate":0.2868020808},
  {"glider":"303 Mosquito" , "glider_and_max_pilot_wgt":450, "max_ballast":0, "V1":100,"W1":-0.68, "V2":120, "W2":-0.92, "V3":150, "W3":-1.45, "wing_area":9.85, "ballast_dump_time":0, "handicap":107, "glider_empty_mass":242, "pilotMass":208, "a":-0.000113333333333333, "b":0.0129333333333333, "c":-0.839999999999999, "minSinkSpeed":57, "minSinkRate":-0.102799267866667},
  {"glider":"304CZ" , "glider_and_max_pilot_wgt":310, "max_ballast":115, "V1":115.03,"W1":-0.86, "V2":174.04, "W2":-1.76, "V3":212.72, "W3":-3.4, "wing_area":0, "ballast_dump_time":0, "handicap":110, "glider_empty_mass":235, "pilotMass":75, "a":-0.000277894568909211, "b":0.0650793307722573, "c":-4.66900202227785, "minSinkSpeed":117, "minSinkRate":2.94528871344705},
  {"glider":"401 Kestrel (17m)" , "glider_and_max_pilot_wgt":367, "max_ballast":33, "V1":95,"W1":-0.62, "V2":110, "W2":-0.76, "V3":175, "W3":-2.01, "wing_area":11.58, "ballast_dump_time":0, "handicap":110, "glider_empty_mass":260, "pilotMass":107, "a":-0.000123717948717949, "b":0.0160288461538462, "c":-1.0261858974359, "minSinkSpeed":65, "minSinkRate":0.0156900974626066},
  {"glider":"604 Kestrel" , "glider_and_max_pilot_wgt":570, "max_ballast":100, "V1":112.97,"W1":-0.72, "V2":150.64, "W2":-1.42, "V3":207.13, "W3":-4.1, "wing_area":16.26, "ballast_dump_time":0, "handicap":114, "glider_empty_mass":455, "pilotMass":115, "a":-0.000306495314392945, "b":0.0622128034931716, "c":-3.83661950352588, "minSinkSpeed":101, "minSinkRate":2.4468831371616},
  {"glider":"AK-8" , "glider_and_max_pilot_wgt":362, "max_ballast":100, "V1":84.1343,"W1":-0.6524, "V2":130, "W2":-0.9474, "V3":170, "W3":-1.838, "wing_area":9.75, "ballast_dump_time":50, "handicap":107, "glider_empty_mass":233, "pilotMass":129, "a":-0.000184394681451484, "b":0.0330534044354452, "c":-2.1280724600778, "minSinkSpeed":90, "minSinkRate":0.846736999238141},
  {"glider":"Antares 18S" , "glider_and_max_pilot_wgt":350, "max_ballast":250, "V1":100,"W1":-0.54, "V2":120, "W2":-0.63, "V3":150, "W3":-1.07, "wing_area":10.97, "ballast_dump_time":0, "handicap":120, "glider_empty_mass":295, "pilotMass":55, "a":-0.000203333333333333, "b":0.0402333333333334, "c":-2.53, "minSinkSpeed":99, "minSinkRate":1.4531040931},
  {"glider":"Antares 18T" , "glider_and_max_pilot_wgt":395, "max_ballast":205, "V1":100,"W1":-0.54, "V2":120, "W2":-0.69, "V3":150, "W3":-1.11, "wing_area":10.97, "ballast_dump_time":0, "handicap":120, "glider_empty_mass":345, "pilotMass":50, "a":-0.00013, "b":0.0211, "c":-1.35, "minSinkSpeed":81, "minSinkRate":0.359101368900001},
  {"glider":"Antares 20E" , "glider_and_max_pilot_wgt":530, "max_ballast":130, "V1":100,"W1":-0.52, "V2":120, "W2":-0.61, "V3":150, "W3":-0.91, "wing_area":12.6, "ballast_dump_time":0, "handicap":123, "glider_empty_mass":475, "pilotMass":55, "a":-0.00011, "b":0.0197, "c":-1.39, "minSinkSpeed":90, "minSinkRate":0.383001089},
  {"glider":"Apis (13m)" , "glider_and_max_pilot_wgt":200, "max_ballast":45, "V1":100,"W1":-0.74, "V2":120, "W2":-1.01, "V3":150, "W3":-1.66, "wing_area":10.36, "ballast_dump_time":0, "handicap":93, "glider_empty_mass":137, "pilotMass":63, "a":-0.000163333333333333, "b":0.0224333333333333, "c":-1.35, "minSinkSpeed":69, "minSinkRate":0.197901840766666},
  {"glider":"Apis 2 (15m)" , "glider_and_max_pilot_wgt":310, "max_ballast":0, "V1":80,"W1":-0.6, "V2":100, "W2":-0.75, "V3":140, "W3":-1.45, "wing_area":12.4, "ballast_dump_time":0, "handicap":98, "glider_empty_mass":215, "pilotMass":95, "a":-0.000166666666666667, "b":0.0225, "c":-1.33333333333333, "minSinkSpeed":68, "minSinkRate":0.196668555555556},
  {"glider":"Arcus" , "glider_and_max_pilot_wgt":700, "max_ballast":185, "V1":110,"W1":-0.64, "V2":140, "W2":-0.88, "V3":180, "W3":-1.47, "wing_area":15.59, "ballast_dump_time":50, "handicap":120, "glider_empty_mass":430, "pilotMass":270, "a":-0.0000964285714285715, "b":0.0161071428571429, "c":-1.245, "minSinkSpeed":84, "minSinkRate":0.108000781071429},
  {"glider":"ASG-29 (18m)" , "glider_and_max_pilot_wgt":355, "max_ballast":225, "V1":85,"W1":-0.47, "V2":90, "W2":-0.48, "V3":185, "W3":-2, "wing_area":10.5, "ballast_dump_time":0, "handicap":121, "glider_empty_mass":280, "pilotMass":75, "a":-0.00014, "b":0.0225, "c":-1.371, "minSinkSpeed":80, "minSinkRate":0.429001568000001},
  {"glider":"ASG-29E (15m)" , "glider_and_max_pilot_wgt":350, "max_ballast":200, "V1":100,"W1":-0.64, "V2":120, "W2":-0.75, "V3":150, "W3":-1.13, "wing_area":9.2, "ballast_dump_time":0, "handicap":114, "glider_empty_mass":315, "pilotMass":35, "a":-0.000143333333333333, "b":0.0260333333333333, "c":-1.81, "minSinkSpeed":91, "minSinkRate":0.559035202877777},
  {"glider":"ASG-29E (18m)" , "glider_and_max_pilot_wgt":400, "max_ballast":200, "V1":90,"W1":-0.499, "V2":95.5, "W2":-0.51, "V3":196.4, "W3":-2.12, "wing_area":10.5, "ballast_dump_time":0, "handicap":121, "glider_empty_mass":325, "pilotMass":75, "a":-0.000131169102140883, "b":0.0223318684471338, "c":-1.44639843290089, "minSinkSpeed":85, "minSinkRate":0.451811847558817},
  {"glider":"ASH-25" , "glider_and_max_pilot_wgt":750, "max_ballast":121, "V1":130.01,"W1":-0.78, "V2":169.96, "W2":-1.4, "V3":219.94, "W3":-2.6, "wing_area":16.31, "ballast_dump_time":0, "handicap":122, "glider_empty_mass":478, "pilotMass":272, "a":-0.0000944090358331513, "b":0.0128004792298091, "c":-0.848432126153155, "minSinkSpeed":68, "minSinkRate":0.0220010675623553},
  {"glider":"ASH-26" , "glider_and_max_pilot_wgt":340, "max_ballast":185, "V1":100,"W1":-0.56, "V2":120, "W2":-0.74, "V3":150, "W3":-1.16, "wing_area":11.7, "ballast_dump_time":0, "handicap":119, "glider_empty_mass":325, "pilotMass":15, "a":-0.0001, "b":0.013, "c":-0.860000000000001, "minSinkSpeed":65, "minSinkRate":-0.0149993500000002},
  {"glider":"ASH-26E" , "glider_and_max_pilot_wgt":435, "max_ballast":90, "V1":90,"W1":-0.51, "V2":96, "W2":-0.53, "V3":185, "W3":-2, "wing_area":11.7, "ballast_dump_time":0, "handicap":119, "glider_empty_mass":360, "pilotMass":75, "a":-0.000138773901044747, "b":0.0224786122609897, "c":-1.40900650502662, "minSinkSpeed":81, "minSinkRate":0.411762648027389},
  {"glider":"ASK-13" , "glider_and_max_pilot_wgt":456, "max_ballast":0, "V1":85,"W1":-0.84, "V2":120, "W2":-1.5, "V3":150, "W3":-2.8, "wing_area":17.5, "ballast_dump_time":44.444, "handicap":79, "glider_empty_mass":296, "pilotMass":160, "a":-0.000376556776556776, "b":0.0583369963369963, "c":-3.07802197802198, "minSinkSpeed":77, "minSinkRate":1.4139376581422},
  {"glider":"ASK-18" , "glider_and_max_pilot_wgt":310, "max_ballast":0, "V1":75,"W1":-0.613, "V2":138, "W2":-1.773, "V3":200, "W3":-4.234, "wing_area":12.99, "ballast_dump_time":0, "handicap":88, "glider_empty_mass":215, "pilotMass":95, "a":-0.000170246799795187, "b":0.0178498699436764, "c":-0.994101996927805, "minSinkSpeed":52, "minSinkRate":-0.0659072526900433},
  {"glider":"ASK-21" , "glider_and_max_pilot_wgt":468, "max_ballast":0, "V1":74.1,"W1":-0.67, "V2":101.9, "W2":-0.9, "V3":166.7, "W3":-2.68, "wing_area":17.95, "ballast_dump_time":50, "handicap":92, "glider_empty_mass":360, "pilotMass":108, "a":-0.000207297564875865, "b":0.0282109901231882, "c":-1.6222028259322, "minSinkSpeed":68, "minSinkRate":0.296147424559668},
  {"glider":"ASK-23" , "glider_and_max_pilot_wgt":330, "max_ballast":0, "V1":100,"W1":-0.85, "V2":120, "W2":-1.19, "V3":150, "W3":-2.02, "wing_area":12.9, "ballast_dump_time":0, "handicap":92, "glider_empty_mass":240, "pilotMass":90, "a":-0.000213333333333334, "b":0.0299333333333334, "c":-1.71, "minSinkSpeed":70, "minSinkRate":0.385336519111111},
  {"glider":"ASW-12" , "glider_and_max_pilot_wgt":394, "max_ballast":189, "V1":95,"W1":-0.57, "V2":148, "W2":-1.48, "V3":183.09, "W3":-2.6, "wing_area":13, "ballast_dump_time":0, "handicap":110, "glider_empty_mass":324, "pilotMass":70, "a":-0.000167420978704717, "b":0.0235134865044915, "c":-1.29280688511662, "minSinkSpeed":70, "minSinkRate":0.353139132282671},
  {"glider":"ASW-15" , "glider_and_max_pilot_wgt":349, "max_ballast":91, "V1":97.56,"W1":-0.77, "V2":156.12, "W2":-1.9, "V3":195.15, "W3":-3.4, "wing_area":11, "ballast_dump_time":0, "handicap":97, "glider_empty_mass":210, "pilotMass":139, "a":-0.000196080820945835, "b":0.0304453345701078, "c":-1.87395868504735, "minSinkSpeed":78, "minSinkRate":0.500780410340751},
  {"glider":"ASW-17" , "glider_and_max_pilot_wgt":522, "max_ballast":151, "V1":114.5,"W1":-0.7, "V2":169.05, "W2":-1.68, "V3":206.5, "W3":-2.9, "wing_area":14.84, "ballast_dump_time":0, "handicap":115, "glider_empty_mass":405, "pilotMass":117, "a":-0.000158821733219181, "b":0.0270687328850961, "c":-1.71717728740674, "minSinkSpeed":85, "minSinkRate":0.583667151895578},
  {"glider":"ASW-19" , "glider_and_max_pilot_wgt":363, "max_ballast":125, "V1":97.47,"W1":-0.74, "V2":155.96, "W2":-1.64, "V3":194.96, "W3":-3.1, "wing_area":11, "ballast_dump_time":47.222, "handicap":100, "glider_empty_mass":240, "pilotMass":123, "a":-0.0002261632142053, "b":0.0419292976930264, "c":-2.67820744235636, "minSinkSpeed":93, "minSinkRate":1.22122200002645},
  {"glider":"ASW-20" , "glider_and_max_pilot_wgt":377, "max_ballast":159, "V1":116.2,"W1":-0.77, "V2":174.3, "W2":-1.89, "V3":213.04, "W3":-3.3, "wing_area":10.5, "ballast_dump_time":0, "handicap":108, "glider_empty_mass":255, "pilotMass":122, "a":-0.00017678005971591, "b":0.0320774989137369, "c":-2.11044322426573, "minSinkSpeed":91, "minSinkRate":0.808612020742568},
  {"glider":"ASW-20BL" , "glider_and_max_pilot_wgt":400, "max_ballast":126, "V1":95,"W1":-0.628, "V2":148, "W2":-1.338, "V3":200, "W3":-2.774, "wing_area":10.49, "ballast_dump_time":0, "handicap":112, "glider_empty_mass":275, "pilotMass":125, "a":-0.000135420554288479, "b":0.019510968277006, "c":-1.25937148386205, "minSinkSpeed":72, "minSinkRate":0.145419552470692},
  {"glider":"ASW-22B" , "glider_and_max_pilot_wgt":597, "max_ballast":303, "V1":80,"W1":-0.4015, "V2":120, "W2":-0.66, "V3":160, "W3":-1.3539, "wing_area":16.31, "ballast_dump_time":0, "handicap":123, "glider_empty_mass":270, "pilotMass":327, "a":-0.0001360625, "b":0.02075, "c":-1.1907, "minSinkSpeed":76, "minSinkRate":0.386301406988296},
  {"glider":"ASW-22BLE" , "glider_and_max_pilot_wgt":465, "max_ballast":285, "V1":100,"W1":-0.47, "V2":120, "W2":-0.63, "V3":150, "W3":-1.04, "wing_area":16.7, "ballast_dump_time":0, "handicap":124, "glider_empty_mass":275, "pilotMass":190, "a":-0.000113333333333333, "b":0.0169333333333333, "c":-1.03, "minSinkSpeed":75, "minSinkRate":0.240000963333333},
  {"glider":"ASW-24" , "glider_and_max_pilot_wgt":350, "max_ballast":159, "V1":108.82,"W1":-0.73, "V2":142.25, "W2":-1.21, "V3":167.41, "W3":-1.8, "wing_area":10, "ballast_dump_time":0, "handicap":107, "glider_empty_mass":230, "pilotMass":120, "a":-0.000155172550860729, "b":0.0246008115907894, "c":-1.5695391838385, "minSinkSpeed":79, "minSinkRate":0.37392683403698},
  {"glider":"ASW-27" , "glider_and_max_pilot_wgt":365, "max_ballast":165, "V1":88.8335,"W1":-0.5939, "V2":130, "W2":-0.8511, "V3":170, "W3":-1.6104, "wing_area":9, "ballast_dump_time":0, "handicap":114, "glider_empty_mass":235, "pilotMass":130, "a":-0.000156896027621207, "b":0.0280863082863621, "c":-1.85077721042867, "minSinkSpeed":90, "minSinkRate":0.676992750816627},
  {"glider":"ASW-28 (15m)" , "glider_and_max_pilot_wgt":310, "max_ballast":200, "V1":92.6,"W1":-0.571, "V2":120.38, "W2":-0.875, "V3":148.16, "W3":-1.394, "wing_area":10.5, "ballast_dump_time":55.555, "handicap":108, "glider_empty_mass":235, "pilotMass":75, "a":-0.000139297711474659, "b":0.0187245020398368, "c":-1.11044444444445, "minSinkSpeed":67, "minSinkRate":0.144098492282734},
  {"glider":"ASW-28 (18m)" , "glider_and_max_pilot_wgt":345, "max_ballast":190, "V1":65,"W1":-0.47, "V2":107, "W2":-0.67, "V3":165, "W3":-2, "wing_area":10.5, "ballast_dump_time":0, "handicap":114, "glider_empty_mass":270, "pilotMass":75, "a":-0.000181691297208539, "b":0.0264889983579639, "c":-1.42413916256158, "minSinkSpeed":73, "minSinkRate":0.509560127425893},
  {"glider":"Blanik L13" , "glider_and_max_pilot_wgt":472, "max_ballast":0, "V1":85,"W1":-0.84, "V2":143, "W2":-3.32, "V3":200, "W3":-9.61, "wing_area":19.1, "ballast_dump_time":0, "handicap":78, "glider_empty_mass":292, "pilotMass":180, "a":-0.000587758752202846, "b":0.0912503748125937, "c":-4.3497248744049, "minSinkSpeed":78, "minSinkRate":2.76783130688477},
  {"glider":"Blanik L13-AC" , "glider_and_max_pilot_wgt":500, "max_ballast":0, "V1":70,"W1":-0.85, "V2":110, "W2":-1.25, "V3":160, "W3":-3.2, "wing_area":17.44, "ballast_dump_time":44.44, "handicap":78, "glider_empty_mass":306, "pilotMass":194, "a":-0.000322222222222222, "b":0.048, "c":-2.63111111111111, "minSinkSpeed":74, "minSinkRate":0.920896572098765},
  {"glider":"Blanik L23" , "glider_and_max_pilot_wgt":510, "max_ballast":0, "V1":95,"W1":-0.94, "V2":148, "W2":-2.6, "V3":200, "W3":-6.37, "wing_area":19.1, "ballast_dump_time":0, "handicap":80, "glider_empty_mass":310, "pilotMass":200, "a":-0.000392183288409704, "b":0.0639797843665768, "c":-3.47862533692723, "minSinkSpeed":82, "minSinkRate":1.76772959336608},
  {"glider":"Carat" , "glider_and_max_pilot_wgt":470, "max_ballast":0, "V1":100,"W1":-0.83, "V2":120, "W2":-1.04, "V3":150, "W3":-1.69, "wing_area":10.58, "ballast_dump_time":0, "handicap":93, "glider_empty_mass":341, "pilotMass":129, "a":-0.000223333333333333, "b":0.0386333333333333, "c":-2.46, "minSinkSpeed":86, "minSinkRate":0.862470956155554},
  {"glider":"Cirrus (18m)" , "glider_and_max_pilot_wgt":330, "max_ballast":100, "V1":100,"W1":-0.74, "V2":120, "W2":-1.06, "V3":150, "W3":-1.88, "wing_area":12.6, "ballast_dump_time":0, "handicap":102, "glider_empty_mass":260, "pilotMass":70, "a":-0.000226666666666667, "b":0.0338666666666666, "c":-1.86, "minSinkSpeed":75, "minSinkRate":0.680003853333333},
  {"glider":"DG-1000 (20m)" , "glider_and_max_pilot_wgt":613, "max_ballast":160, "V1":106,"W1":-0.62, "V2":153, "W2":-1.53, "V3":200, "W3":-3.2, "wing_area":17.51, "ballast_dump_time":0, "handicap":111, "glider_empty_mass":415, "pilotMass":198, "a":-0.000172023540063377, "b":0.0251923947487551, "c":-1.35753734721594, "minSinkSpeed":73, "minSinkRate":0.481509629666365},
  {"glider":"DG-100" , "glider_and_max_pilot_wgt":300, "max_ballast":100, "V1":100,"W1":-0.73, "V2":120, "W2":-1, "V3":150, "W3":-1.7, "wing_area":11, "ballast_dump_time":0, "handicap":100, "glider_empty_mass":230, "pilotMass":70, "a":-0.000196666666666667, "b":0.0297666666666667, "c":-1.74, "minSinkSpeed":76, "minSinkRate":0.522269606177777},
  {"glider":"DG-200" , "glider_and_max_pilot_wgt":300, "max_ballast":120, "V1":100,"W1":-0.68, "V2":120, "W2":-0.86, "V3":150, "W3":-1.3, "wing_area":10, "ballast_dump_time":0, "handicap":107, "glider_empty_mass":230, "pilotMass":70, "a":-0.000113333333333333, "b":0.0159333333333334, "c":-1.14, "minSinkSpeed":70, "minSinkRate":-0.0246657675555555},
  {"glider":"DG-300" , "glider_and_max_pilot_wgt":310, "max_ballast":190, "V1":95,"W1":-0.66, "V2":140, "W2":-1.28, "V3":160, "W3":-1.7, "wing_area":10.27, "ballast_dump_time":0, "handicap":104, "glider_empty_mass":235, "pilotMass":75, "a":-0.000111111111111111, "b":0.0123333333333333, "c":-0.828888888888888, "minSinkSpeed":56, "minSinkRate":-0.138221530864198},
  {"glider":"DG-400 (15m)" , "glider_and_max_pilot_wgt":440, "max_ballast":90, "V1":115,"W1":-0.76, "V2":160.53, "W2":-1.22, "V3":210.22, "W3":-2.3, "wing_area":10, "ballast_dump_time":0, "handicap":107, "glider_empty_mass":306, "pilotMass":134, "a":-0.000122154241163032, "b":0.0235539294271935, "c":-1.85321204474614, "minSinkSpeed":96, "minSinkRate":0.407966612743657},
  {"glider":"DG-400 (17m)" , "glider_and_max_pilot_wgt":444, "max_ballast":90, "V1":118.28,"W1":-0.68, "V2":163.77, "W2":-1.15, "V3":198.35, "W3":-1.8, "wing_area":10.57, "ballast_dump_time":0, "handicap":109, "glider_empty_mass":310, "pilotMass":134, "a":-0.000105720636883353, "b":0.0194865645469967, "c":-1.50582239847178, "minSinkSpeed":92, "minSinkRate":0.286942568122398},
  {"glider":"DG-500 (20m)" , "glider_and_max_pilot_wgt":659, "max_ballast":100, "V1":115.4,"W1":-0.71, "V2":152.01, "W2":-1.28, "V3":190.02, "W3":-2.3, "wing_area":18.29, "ballast_dump_time":0, "handicap":104, "glider_empty_mass":390, "pilotMass":269, "a":-0.00015097194966617, "b":0.024801892534691, "c":-1.56162078928701, "minSinkSpeed":82, "minSinkRate":0.472136267545075},
  {"glider":"DG-600 (15m)" , "glider_and_max_pilot_wgt":327, "max_ballast":180, "V1":100,"W1":-0.6, "V2":120, "W2":-0.76, "V3":150, "W3":-1.19, "wing_area":10.95, "ballast_dump_time":0, "handicap":110, "glider_empty_mass":255, "pilotMass":72, "a":-0.000126666666666667, "b":0.0198666666666666, "c":-1.32, "minSinkSpeed":78, "minSinkRate":0.229601251466667},
  {"glider":"DG-800B (15m)" , "glider_and_max_pilot_wgt":468, "max_ballast":100, "V1":103.61,"W1":-0.6535, "V2":130, "W2":-0.8915, "V3":170, "W3":-1.4807, "wing_area":10.68, "ballast_dump_time":52.8, "handicap":113, "glider_empty_mass":340, "pilotMass":128, "a":-0.0000860285037015019, "b":0.0110785511104506, "c":-0.877829931803193, "minSinkSpeed":64, "minSinkRate":-0.168802187076535},
  {"glider":"DG-800B (18m)" , "glider_and_max_pilot_wgt":472, "max_ballast":100, "V1":90.0086,"W1":-0.5496, "V2":130, "W2":-0.792, "V3":170, "W3":-1.4248, "wing_area":11.81, "ballast_dump_time":52.8, "handicap":119, "glider_empty_mass":344, "pilotMass":128, "a":-0.000121996824906381, "b":0.0207790474719142, "c":-1.43152983043101, "minSinkSpeed":85, "minSinkRate":0.334690469755844},
  {"glider":"DG-800S (15m)" , "glider_and_max_pilot_wgt":370, "max_ballast":150, "V1":92.1255,"W1":-0.5811, "V2":130, "W2":-0.9754, "V3":170, "W3":-1.6933, "wing_area":10.68, "ballast_dump_time":52.8, "handicap":113, "glider_empty_mass":260, "pilotMass":110, "a":-0.0000967813791283515, "b":0.0110869137385055, "c":-0.781093478736568, "minSinkSpeed":57, "minSinkRate":-0.149138861743543},
  {"glider":"DG-800S (18m)" , "glider_and_max_pilot_wgt":350, "max_ballast":150, "V1":77.5081,"W1":-0.4733, "V2":130, "W2":-0.9257, "V3":170, "W3":-1.7948, "wing_area":11.81, "ballast_dump_time":52.8, "handicap":119, "glider_empty_mass":264, "pilotMass":86, "a":-0.000141731626614455, "b":0.0207919879843365, "c":-1.23339394817946, "minSinkSpeed":73, "minSinkRate":0.284422641090449},
  {"glider":"Dimona" , "glider_and_max_pilot_wgt":670, "max_ballast":100, "V1":100,"W1":-1.29, "V2":120, "W2":-1.61, "V3":150, "W3":-2.45, "wing_area":15.3, "ballast_dump_time":0, "handicap":68, "glider_empty_mass":470, "pilotMass":200, "a":-0.00024, "b":0.0368, "c":-2.57, "minSinkSpeed":77, "minSinkRate":0.2636044352},
  {"glider":"Discus 2b" , "glider_and_max_pilot_wgt":312, "max_ballast":200, "V1":105,"W1":-0.66, "V2":150, "W2":-1.05, "V3":200, "W3":-2, "wing_area":10.6, "ballast_dump_time":0, "handicap":108, "glider_empty_mass":252, "pilotMass":60, "a":-0.000108771929824561, "b":0.0190701754385965, "c":-1.46315789473684, "minSinkSpeed":88, "minSinkRate":0.215018585016928},
  {"glider":"Discus 2c (18m)" , "glider_and_max_pilot_wgt":377, "max_ballast":188, "V1":100,"W1":-0.57, "V2":120, "W2":-0.76, "V3":150, "W3":-1.33, "wing_area":11.36, "ballast_dump_time":55.555, "handicap":114, "glider_empty_mass":280, "pilotMass":97, "a":-0.00019, "b":0.0323, "c":-1.9, "minSinkSpeed":85, "minSinkRate":0.8455030685},
  {"glider":"Discus" , "glider_and_max_pilot_wgt":350, "max_ballast":182, "V1":95,"W1":-0.63, "V2":140, "W2":-1.23, "V3":180, "W3":-2.29, "wing_area":10.58, "ballast_dump_time":55.555, "handicap":107, "glider_empty_mass":233, "pilotMass":117, "a":-0.000154901960784314, "b":0.0230686274509804, "c":-1.42352941176471, "minSinkSpeed":74, "minSinkRate":0.283550795209534},
  {"glider":"Duo Discus" , "glider_and_max_pilot_wgt":615, "max_ballast":80, "V1":103,"W1":-0.64, "V2":152, "W2":-1.25, "V3":200, "W3":-2.51, "wing_area":16.4, "ballast_dump_time":0, "handicap":112, "glider_empty_mass":420, "pilotMass":195, "a":-0.0001422785609089, "b":0.0238320534399327, "c":-1.58526825163055, "minSinkSpeed":84, "minSinkRate":0.416625937751662},
  {"glider":"Duo Discus T" , "glider_and_max_pilot_wgt":615, "max_ballast":80, "V1":103,"W1":-0.64, "V2":152, "W2":-1.25, "V3":200, "W3":-2.51, "wing_area":16.4, "ballast_dump_time":0, "handicap":112, "glider_empty_mass":445, "pilotMass":170, "a":-0.0001422785609089, "b":0.0238320534399327, "c":-1.58526825163055, "minSinkSpeed":84, "minSinkRate":0.416625937751662},
  {"glider":"Duo Discus xT" , "glider_and_max_pilot_wgt":700, "max_ballast":50, "V1":110,"W1":-0.664, "V2":155, "W2":-1.206, "V3":200, "W3":-2.287, "wing_area":16.4, "ballast_dump_time":50, "handicap":113, "glider_empty_mass":445, "pilotMass":255, "a":-0.000133086419753086, "b":0.0232234567901235, "c":-1.60823456790123, "minSinkSpeed":87, "minSinkRate":0.412207713783082},
  {"glider":"EB 28" , "glider_and_max_pilot_wgt":670, "max_ballast":180, "V1":100,"W1":-0.46, "V2":120, "W2":-0.61, "V3":150, "W3":-0.96, "wing_area":16.8, "ballast_dump_time":0, "handicap":125, "glider_empty_mass":570, "pilotMass":100, "a":-0.0000833333333333334, "b":0.0108333333333334, "c":-0.710000000000001, "minSinkSpeed":65, "minSinkRate":-0.00583288194444431},
  {"glider":"EB 28 Edition" , "glider_and_max_pilot_wgt":670, "max_ballast":180, "V1":100,"W1":-0.47, "V2":120, "W2":-0.63, "V3":150, "W3":-0.97, "wing_area":16.5, "ballast_dump_time":0, "handicap":125, "glider_empty_mass":570, "pilotMass":100, "a":-0.0000666666666666667, "b":0.00666666666666667, "c":-0.47, "minSinkSpeed":50, "minSinkRate":-0.136666444444445},
  {"glider":"G 102 Astir CS" , "glider_and_max_pilot_wgt":330, "max_ballast":90, "V1":75,"W1":-0.7, "V2":93, "W2":-0.74, "V3":185, "W3":-3.1, "wing_area":12.4, "ballast_dump_time":0, "handicap":96, "glider_empty_mass":255, "pilotMass":75, "a":-0.000212999560825648, "b":0.0335617039964866, "c":-2.01900527009222, "minSinkSpeed":79, "minSinkRate":0.632372929766437},
  {"glider":"G 102 Club Astir IIIb" , "glider_and_max_pilot_wgt":380, "max_ballast":0, "V1":75,"W1":-0.6, "V2":100, "W2":-0.7, "V3":180, "W3":-3.1, "wing_area":12.4, "ballast_dump_time":0, "handicap":91, "glider_empty_mass":255, "pilotMass":125, "a":-0.000247619047619048, "b":0.0393333333333334, "c":-2.15714285714286, "minSinkSpeed":79, "minSinkRate":0.950195320090703},
  {"glider":"G 102 Standard Astir III" , "glider_and_max_pilot_wgt":380, "max_ballast":70, "V1":75,"W1":-0.6, "V2":100, "W2":-0.7, "V3":180, "W3":-2.8, "wing_area":12.4, "ballast_dump_time":0, "handicap":100, "glider_empty_mass":260, "pilotMass":120, "a":-0.000211904761904762, "b":0.0330833333333333, "c":-1.88928571428571, "minSinkSpeed":78, "minSinkRate":0.691217788197279},
  {"glider":"G 103 Twin 2" , "glider_and_max_pilot_wgt":580, "max_ballast":0, "V1":99,"W1":-0.8, "V2":175.01, "W2":-1.95, "V3":225.02, "W3":-3.8, "wing_area":17.52, "ballast_dump_time":0, "handicap":92, "glider_empty_mass":390, "pilotMass":190, "a":-0.000173488440466804, "b":0.0324079793602317, "c":-2.30802975164778, "minSinkSpeed":93, "minSinkRate":0.705915127989984},
  {"glider":"G 104 Speed Astir" , "glider_and_max_pilot_wgt":351, "max_ballast":90, "V1":90,"W1":-0.63, "V2":105, "W2":-0.72, "V3":157, "W3":-2, "wing_area":11.5, "ballast_dump_time":0, "handicap":105, "glider_empty_mass":265, "pilotMass":86, "a":-0.000277841561423651, "b":0.0481791044776119, "c":-2.7156027554535, "minSinkSpeed":87, "minSinkRate":1.47598605014493},
  {"glider":"Genesis II" , "glider_and_max_pilot_wgt":374, "max_ballast":151, "V1":94,"W1":-0.61, "V2":141.05, "W2":-1.18, "V3":172.4, "W3":-2, "wing_area":11.24, "ballast_dump_time":0, "handicap":107, "glider_empty_mass":240, "pilotMass":134, "a":-0.00017910112654146, "b":0.0299829482739103, "c":-1.84585958362723, "minSinkSpeed":84, "minSinkRate":0.672710765867174},
  {"glider":"Glasfluegel 304" , "glider_and_max_pilot_wgt":305, "max_ballast":145, "V1":100,"W1":-0.78, "V2":120, "W2":-0.97, "V3":150, "W3":-1.43, "wing_area":9.9, "ballast_dump_time":0, "handicap":110, "glider_empty_mass":235, "pilotMass":70, "a":-0.000116666666666667, "b":0.0161666666666667, "c":-1.23, "minSinkSpeed":69, "minSinkRate":-0.114499060833333},
  {"glider":"H-201 Std Libelle" , "glider_and_max_pilot_wgt":304, "max_ballast":50, "V1":97,"W1":-0.79, "V2":152.43, "W2":-1.91, "V3":190.54, "W3":-3.3, "wing_area":9.8, "ballast_dump_time":41.666, "handicap":98, "glider_empty_mass":185, "pilotMass":119, "a":-0.000173911714432333, "b":0.0231731341284033, "c":-1.4014586893613, "minSinkSpeed":67, "minSinkRate":0.151143323675778},
  {"glider":"H-205 Club Libelle" , "glider_and_max_pilot_wgt":295, "max_ballast":0, "V1":100,"W1":-0.85, "V2":120, "W2":-1.21, "V3":150, "W3":-2.01, "wing_area":9.8, "ballast_dump_time":41.666, "handicap":96, "glider_empty_mass":200, "pilotMass":95, "a":-0.000173333333333333, "b":0.0201333333333334, "c":-1.13, "minSinkSpeed":58, "minSinkRate":0.0377350759111108},
  {"glider":"H-301 Libelle" , "glider_and_max_pilot_wgt":300, "max_ballast":50, "V1":94,"W1":-0.68, "V2":147.71, "W2":-2.03, "V3":184.64, "W3":-4.1, "wing_area":9.8, "ballast_dump_time":41.666, "handicap":100, "glider_empty_mass":180, "pilotMass":120, "a":-0.000341096713123992, "b":0.0573115023549309, "c":-3.05335066419991, "minSinkSpeed":84, "minSinkRate":1.76082530675957},
  {"glider":"IS-28B2" , "glider_and_max_pilot_wgt":590, "max_ballast":0, "V1":100,"W1":-0.82, "V2":160, "W2":-2.28, "V3":200, "W3":-4.27, "wing_area":18.24, "ballast_dump_time":0, "handicap":84, "glider_empty_mass":375, "pilotMass":215, "a":-0.000254166666666667, "b":0.04175, "c":-2.45333333333333, "minSinkSpeed":82, "minSinkRate":0.970171963923609},
  {"glider":"IS-29D2 Lark" , "glider_and_max_pilot_wgt":360, "max_ballast":0, "V1":100,"W1":-0.82, "V2":135.67, "W2":-1.55, "V3":184.12, "W3":-3.3, "wing_area":10.4, "ballast_dump_time":0, "handicap":96, "glider_empty_mass":240, "pilotMass":120, "a":-0.000186095268363621, "b":0.0233916948276908, "c":-1.29821679913287, "minSinkSpeed":63, "minSinkRate":0.175462156792934},
  {"glider":"Janus (18m)" , "glider_and_max_pilot_wgt":498, "max_ballast":240, "V1":100,"W1":-0.71, "V2":120, "W2":-0.92, "V3":150, "W3":-1.46, "wing_area":16.6, "ballast_dump_time":0, "handicap":102, "glider_empty_mass":405, "pilotMass":93, "a":-0.00015, "b":0.0225, "c":-1.46, "minSinkSpeed":75, "minSinkRate":0.2275016875},
  {"glider":"Janus C FG" , "glider_and_max_pilot_wgt":603, "max_ballast":170, "V1":115.5,"W1":-0.76, "V2":171.79, "W2":-1.98, "V3":209.96, "W3":-4, "wing_area":17.4, "ballast_dump_time":47.222, "handicap":106, "glider_empty_mass":405, "pilotMass":198, "a":-0.000330803150746172, "b":0.0733629605390332, "c":-4.82042521051671, "minSinkSpeed":111, "minSinkRate":3.3228755561264},
  {"glider":"Janus C RG" , "glider_and_max_pilot_wgt":519, "max_ballast":240, "V1":90,"W1":-0.6, "V2":120, "W2":-0.88, "V3":160, "W3":-1.64, "wing_area":17.3, "ballast_dump_time":50, "handicap":108, "glider_empty_mass":405, "pilotMass":114, "a":-0.000138095238095238, "b":0.0196666666666666, "c":-1.25142857142857, "minSinkSpeed":71, "minSinkRate":0.144906115895692},
  {"glider":"JS-1B (18m)" , "glider_and_max_pilot_wgt":405, "max_ballast":180, "V1":108,"W1":-0.57, "V2":152, "W2":-1.06, "V3":180, "W3":-1.65, "wing_area":11.25, "ballast_dump_time":56.3, "handicap":121, "glider_empty_mass":310, "pilotMass":95, "a":-0.000137987012987013, "b":0.0247402597402597, "c":-1.63246753246753, "minSinkSpeed":90, "minSinkRate":0.594157557793261},
  {"glider":"JS-1C (21m)" , "glider_and_max_pilot_wgt":441, "max_ballast":180, "V1":108,"W1":-0.52, "V2":156, "W2":-1.1, "V3":180, "W3":-1.62, "wing_area":12.25, "ballast_dump_time":56.3, "handicap":126, "glider_empty_mass":330, "pilotMass":111, "a":-0.000133101851851852, "b":0.0230555555555555, "c":-1.4575, "minSinkSpeed":87, "minSinkRate":0.54833487463429},
  {"glider":"JS-3 (15m)" , "glider_and_max_pilot_wgt":350, "max_ballast":158, "V1":100,"W1":-0.6, "V2":130, "W2":-0.8, "V3":160, "W3":-1.2, "wing_area":8.75, "ballast_dump_time":57.5, "handicap":116, "glider_empty_mass":270, "pilotMass":80, "a":-0.000111111111111111, "b":0.0188888888888889, "c":-1.37777777777778, "minSinkSpeed":85, "minSinkRate":0.227778827160493},
  {"glider":"JS-3 (18m)" , "glider_and_max_pilot_wgt":398, "max_ballast":158, "V1":100,"W1":-0.55, "V2":130, "W2":-0.72, "V3":160, "W3":-1.12, "wing_area":9.95, "ballast_dump_time":57.5, "handicap":122, "glider_empty_mass":282, "pilotMass":116, "a":-0.000127777777777778, "b":0.0237222222222222, "c":-1.64444444444445, "minSinkSpeed":93, "minSinkRate":0.561723740648149},
  {"glider":"Ka 2b" , "glider_and_max_pilot_wgt":418, "max_ballast":0, "V1":87,"W1":-0.9, "V2":120, "W2":-1.5, "V3":150, "W3":-2.6, "wing_area":17.5, "ballast_dump_time":0, "handicap":78, "glider_empty_mass":278, "pilotMass":140, "a":-0.000293410293410294, "b":0.0425541125541126, "c":-2.38138528138528, "minSinkSpeed":73, "minSinkRate":0.725071219605755},
  {"glider":"Ka 4 Rhoenlerche" , "glider_and_max_pilot_wgt":360, "max_ballast":0, "V1":65,"W1":-0.95, "V2":120, "W2":-2.5, "V3":140, "W3":-3.5, "wing_area":16.34, "ballast_dump_time":0, "handicap":54, "glider_empty_mass":220, "pilotMass":140, "a":-0.000290909090909091, "b":0.0256363636363636, "c":-1.38727272727273, "minSinkSpeed":44, "minSinkRate":-0.259269003636363},
  {"glider":"Ka 6CR" , "glider_and_max_pilot_wgt":310, "max_ballast":0, "V1":64.83,"W1":-0.67, "V2":130, "W2":-2.26, "V3":170, "W3":-4.69, "wing_area":12.5, "ballast_dump_time":0, "handicap":82, "glider_empty_mass":185, "pilotMass":125, "a":-0.000345652476785979, "b":0.0429457430357938, "c":-2.00141973697014, "minSinkSpeed":62, "minSinkRate":0.661223738738424},
  {"glider":"Ka 6E" , "glider_and_max_pilot_wgt":310, "max_ballast":0, "V1":87.35,"W1":-0.81, "V2":141.92, "W2":-2.03, "V3":174.68, "W3":-3.5, "wing_area":12.4, "ballast_dump_time":0, "handicap":85, "glider_empty_mass":185, "pilotMass":125, "a":-0.00025781734430225, "b":0.0367531763342973, "c":-2.05323781488446, "minSinkSpeed":71, "minSinkRate":0.556242424205242},
  {"glider":"Ka 7" , "glider_and_max_pilot_wgt":445, "max_ballast":0, "V1":87,"W1":-0.92, "V2":120, "W2":-1.55, "V3":150, "W3":-2.7, "wing_area":17.5, "ballast_dump_time":0, "handicap":78, "glider_empty_mass":285, "pilotMass":160, "a":-0.000305435305435305, "b":0.0441341991341991, "c":-2.4478354978355, "minSinkSpeed":72, "minSinkRate":0.729833556759098},
  {"glider":"Ka 8" , "glider_and_max_pilot_wgt":290, "max_ballast":0, "V1":74.1,"W1":-0.76, "V2":101.9, "W2":-1.27, "V3":166.7, "W3":-4.64, "wing_area":14.15, "ballast_dump_time":0, "handicap":76, "glider_empty_mass":190, "pilotMass":100, "a":-0.00036350808961662, "b":0.0456321000315178, "c":-2.14538475878764, "minSinkSpeed":63, "minSinkRate":0.72944586790025},
  {"glider":"L 33 Solo" , "glider_and_max_pilot_wgt":330, "max_ballast":0, "V1":87.2,"W1":-0.8, "V2":135.64, "W2":-1.73, "V3":174.4, "W3":-3.4, "wing_area":11, "ballast_dump_time":0, "handicap":86, "glider_empty_mass":210, "pilotMass":120, "a":-0.000273929429258662, "b":0.0418434249325981, "c":-2.36583110274837, "minSinkSpeed":76, "minSinkRate":0.814274894966332},
  {"glider":"LAK-12" , "glider_and_max_pilot_wgt":430, "max_ballast":190, "V1":75,"W1":-0.48, "V2":125, "W2":-0.88, "V3":175, "W3":-1.97, "wing_area":14.63, "ballast_dump_time":48.611, "handicap":114, "glider_empty_mass":360, "pilotMass":70, "a":-0.000138, "b":0.0196, "c":-1.17375, "minSinkSpeed":71, "minSinkRate":0.217851352124},
  {"glider":"LAK-17 (15m)" , "glider_and_max_pilot_wgt":285, "max_ballast":215, "V1":100,"W1":-0.6, "V2":120, "W2":-0.72, "V3":150, "W3":-1.09, "wing_area":9.06, "ballast_dump_time":0, "handicap":113, "glider_empty_mass":220, "pilotMass":65, "a":-0.000126666666666667, "b":0.0218666666666667, "c":-1.52, "minSinkSpeed":86, "minSinkRate":0.360534713155557},
  {"glider":"LAK-17 (18m)" , "glider_and_max_pilot_wgt":295, "max_ballast":205, "V1":100,"W1":-0.56, "V2":120, "W2":-0.74, "V3":150, "W3":-1.16, "wing_area":9.8, "ballast_dump_time":0, "handicap":119, "glider_empty_mass":225, "pilotMass":70, "a":-0.0001, "b":0.013, "c":-0.860000000000001, "minSinkSpeed":65, "minSinkRate":-0.0149993500000002},
  {"glider":"LAK17a (15m)" , "glider_and_max_pilot_wgt":285, "max_ballast":180, "V1":95,"W1":-0.574, "V2":148, "W2":-1.31, "V3":200, "W3":-2.885, "wing_area":9.06, "ballast_dump_time":0, "handicap":113, "glider_empty_mass":220, "pilotMass":65, "a":-0.000156206372244108, "b":0.0240713560024881, "c":-1.45101631073329, "minSinkSpeed":77, "minSinkRate":0.402479980291456},
  {"glider":"LAK17a (18m)" , "glider_and_max_pilot_wgt":298, "max_ballast":180, "V1":115,"W1":-0.68, "V2":158, "W2":-1.379, "V3":200, "W3":-2.975, "wing_area":9.8, "ballast_dump_time":0, "handicap":119, "glider_empty_mass":225, "pilotMass":73, "a":-0.000255813953488372, "b":0.0535813953488372, "c":-3.45872093023256, "minSinkSpeed":105, "minSinkRate":2.16733245267712},
  {"glider":"LAK-19 (15m)" , "glider_and_max_pilot_wgt":285, "max_ballast":195, "V1":100,"W1":-0.64, "V2":120, "W2":-0.85, "V3":150, "W3":-1.41, "wing_area":9.06, "ballast_dump_time":0, "handicap":108, "glider_empty_mass":220, "pilotMass":65, "a":-0.000163333333333333, "b":0.0254333333333333, "c":-1.55, "minSinkSpeed":78, "minSinkRate":0.433802080866667},
  {"glider":"LAK-19 (18m)" , "glider_and_max_pilot_wgt":295, "max_ballast":185, "V1":100,"W1":-0.6, "V2":120, "W2":-0.82, "V3":150, "W3":-1.34, "wing_area":9.8, "ballast_dump_time":0, "handicap":114, "glider_empty_mass":226, "pilotMass":69, "a":-0.000126666666666667, "b":0.0168666666666667, "c":-1.02, "minSinkSpeed":67, "minSinkRate":0.110067741644445},
  {"glider":"LS-10s (15m)" , "glider_and_max_pilot_wgt":370, "max_ballast":170, "V1":100,"W1":-0.64, "V2":120, "W2":-0.8, "V3":150, "W3":-1.26, "wing_area":10.27, "ballast_dump_time":0, "handicap":113, "glider_empty_mass":288, "pilotMass":82, "a":-0.000146666666666667, "b":0.0242666666666667, "c":-1.6, "minSinkSpeed":83, "minSinkRate":0.414135118755555},
  {"glider":"LS-10s (18m)" , "glider_and_max_pilot_wgt":380, "max_ballast":220, "V1":100,"W1":-0.58, "V2":120, "W2":-0.75, "V3":150, "W3":-1.21, "wing_area":11.45, "ballast_dump_time":0, "handicap":119, "glider_empty_mass":295, "pilotMass":85, "a":-0.000136666666666667, "b":0.0215666666666667, "c":-1.37, "minSinkSpeed":79, "minSinkRate":0.333768142211111},
  {"glider":"LS-1c" , "glider_and_max_pilot_wgt":350, "max_ballast":91, "V1":115.87,"W1":-1.02, "V2":154.49, "W2":-1.84, "V3":193.12, "W3":-3.3, "wing_area":9.74, "ballast_dump_time":0, "handicap":98, "glider_empty_mass":200, "pilotMass":150, "a":-0.000214394022714847, "b":0.0367310459718644, "c":-2.39760282757504, "minSinkSpeed":86, "minSinkRate":0.761271078977833},
  {"glider":"LS-1f" , "glider_and_max_pilot_wgt":345, "max_ballast":80, "V1":100,"W1":-0.75, "V2":120, "W2":-0.98, "V3":150, "W3":-1.6, "wing_area":9.74, "ballast_dump_time":0, "handicap":100, "glider_empty_mass":230, "pilotMass":115, "a":-0.000183333333333333, "b":0.0288333333333334, "c":-1.8, "minSinkSpeed":79, "minSinkRate":0.477835988611111},
  {"glider":"LS-3 (17m)" , "glider_and_max_pilot_wgt":325, "max_ballast":0, "V1":100,"W1":-0.61, "V2":120, "W2":-0.84, "V3":150, "W3":-1.53, "wing_area":11.22, "ballast_dump_time":0, "handicap":109, "glider_empty_mass":255, "pilotMass":70, "a":-0.00023, "b":0.0391, "c":-2.22, "minSinkSpeed":85, "minSinkRate":1.1035044965},
  {"glider":"LS-3" , "glider_and_max_pilot_wgt":383, "max_ballast":121, "V1":93,"W1":-0.64, "V2":127, "W2":-0.93, "V3":148.2, "W3":-1.28, "wing_area":10.5, "ballast_dump_time":0, "handicap":107, "glider_empty_mass":270, "pilotMass":113, "a":-0.000144565619520983, "b":0.0232750245299104, "c":-1.55422923804468, "minSinkSpeed":80, "minSinkRate":0.307774396285615},
  {"glider":"LS-4" , "glider_and_max_pilot_wgt":361, "max_ballast":121, "V1":100,"W1":-0.69, "V2":120, "W2":-0.87, "V3":150, "W3":-1.44, "wing_area":10.5, "ballast_dump_time":0, "handicap":104, "glider_empty_mass":235, "pilotMass":126, "a":-0.0002, "b":0.035, "c":-2.19, "minSinkSpeed":88, "minSinkRate":0.890003519999999},
  {"glider":"LS-5" , "glider_and_max_pilot_wgt":461, "max_ballast":120, "V1":75,"W1":-0.45, "V2":135, "W2":-1, "V3":172.5, "W3":-1.9, "wing_area":13.9, "ballast_dump_time":0, "handicap":118, "glider_empty_mass":361, "pilotMass":100, "a":-0.000152136752136752, "b":0.0227820512820513, "c":-1.30288461538461, "minSinkSpeed":75, "minSinkRate":0.405770966688583},
  {"glider":"LS-6 (15m)" , "glider_and_max_pilot_wgt":327, "max_ballast":160, "V1":90,"W1":-0.6, "V2":100, "W2":-0.658, "V3":183, "W3":-1.965, "wing_area":10.53, "ballast_dump_time":0, "handicap":111, "glider_empty_mass":265, "pilotMass":62, "a":-0.000106956859696852, "b":0.0145218033424018, "c":-1.04061173727166, "minSinkSpeed":68, "minSinkRate":-0.0531283320839919},
  {"glider":"LS-6 (18m)" , "glider_and_max_pilot_wgt":330, "max_ballast":140, "V1":90,"W1":-0.51, "V2":100, "W2":-0.57, "V3":183, "W3":-2, "wing_area":11.4, "ballast_dump_time":0, "handicap":117, "glider_empty_mass":272, "pilotMass":58, "a":-0.000120741028630652, "b":0.0169407954398238, "c":-1.05666925767587, "minSinkSpeed":70, "minSinkRate":0.129187443599522},
  {"glider":"LS-7wl" , "glider_and_max_pilot_wgt":350, "max_ballast":150, "V1":103.77,"W1":-0.73, "V2":155.65, "W2":-1.47, "V3":180, "W3":-2.66, "wing_area":9.8, "ballast_dump_time":0, "handicap":107, "glider_empty_mass":235, "pilotMass":115, "a":-0.000453980730977272, "b":0.103507995802213, "c":-6.58246356073479, "minSinkSpeed":114, "minSinkRate":5.217471455947},
  {"glider":"LS-8 (15m)" , "glider_and_max_pilot_wgt":325, "max_ballast":185, "V1":70,"W1":-0.51, "V2":115, "W2":-0.85, "V3":173, "W3":-2, "wing_area":10.5, "ballast_dump_time":0, "handicap":108, "glider_empty_mass":240, "pilotMass":85, "a":-0.000119145928653796, "b":0.0144864412453967, "c":-0.940235836774169, "minSinkSpeed":61, "minSinkRate":-0.0565620548640783},
  {"glider":"LS-8 (18m)" , "glider_and_max_pilot_wgt":325, "max_ballast":185, "V1":80,"W1":-0.51, "V2":94, "W2":-0.56, "V3":173, "W3":-2, "wing_area":11.4, "ballast_dump_time":0, "handicap":114, "glider_empty_mass":250, "pilotMass":75, "a":-0.000157595908922981, "b":0.0238502595811701, "c":-1.40940694938653, "minSinkSpeed":76, "minSinkRate":0.403214666354157},
  {"glider":"Mini Nimbus" , "glider_and_max_pilot_wgt":345, "max_ballast":155, "V1":100,"W1":-0.69, "V2":120, "W2":-0.92, "V3":150, "W3":-1.45, "wing_area":9.86, "ballast_dump_time":55.555, "handicap":107, "glider_empty_mass":235, "pilotMass":110, "a":-0.000123333333333333, "b":0.0156333333333333, "c":-1.02, "minSinkSpeed":63, "minSinkRate":-0.0350990417},
  {"glider":"Nimbus 2" , "glider_and_max_pilot_wgt":493, "max_ballast":159, "V1":119.83,"W1":-0.75, "V2":179.75, "W2":-2.14, "V3":219.69, "W3":-3.8, "wing_area":14.41, "ballast_dump_time":44.444, "handicap":114, "glider_empty_mass":350, "pilotMass":143, "a":-0.000183904934103197, "b":0.0318966433629081, "c":-1.93144172955006, "minSinkSpeed":87, "minSinkRate":0.843569185452106},
  {"glider":"Nimbus 3" , "glider_and_max_pilot_wgt":527, "max_ballast":159, "V1":116.18,"W1":-0.67, "V2":174.28, "W2":-1.81, "V3":232.37, "W3":-3.8, "wing_area":16.7, "ballast_dump_time":52.777, "handicap":122, "glider_empty_mass":396, "pilotMass":131, "a":-0.000125964752651006, "b":0.0169663795421024, "c":-0.940907894200834, "minSinkSpeed":67, "minSinkRate":0.195840598216996},
  {"glider":"Nimbus 3DM" , "glider_and_max_pilot_wgt":820, "max_ballast":168, "V1":114.97,"W1":-0.57, "V2":157.42, "W2":-0.98, "V3":222.24, "W3":-2.3, "wing_area":16.7, "ballast_dump_time":52.777, "handicap":121, "glider_empty_mass":595, "pilotMass":225, "a":-0.0000998010952395415, "b":0.0175263986597427, "c":-1.26582910710385, "minSinkSpeed":88, "minSinkRate":0.276494851456265},
  {"glider":"Nimbus 3D" , "glider_and_max_pilot_wgt":712, "max_ballast":168, "V1":93.64,"W1":-0.46, "V2":175.42, "W2":-1.48, "V3":218.69, "W3":-2.5, "wing_area":16.7, "ballast_dump_time":52.777, "handicap":121, "glider_empty_mass":485, "pilotMass":227, "a":-0.0000887679096251666, "b":0.0114114066030724, "c":-0.750207172666068, "minSinkSpeed":64, "minSinkRate":-0.0198766457659633},
  {"glider":"Nimbus 3T" , "glider_and_max_pilot_wgt":577, "max_ballast":310, "V1":141.7,"W1":-0.99, "V2":182.35, "W2":-1.89, "V3":243.13, "W3":-4, "wing_area":16.7, "ballast_dump_time":52.777, "handicap":121, "glider_empty_mass":422, "pilotMass":155, "a":-0.000123978561518206, "b":0.0180350314577605, "c":-1.05621205848238, "minSinkSpeed":73, "minSinkRate":0.260346359994047},
  {"glider":"Nimbus 4" , "glider_and_max_pilot_wgt":597, "max_ballast":303, "V1":85.1,"W1":-0.41, "V2":127.98, "W2":-0.75, "V3":162.74, "W3":-1.4, "wing_area":17.8, "ballast_dump_time":50, "handicap":124, "glider_empty_mass":470, "pilotMass":127, "a":-0.000138724243920559, "b":0.0216302574169807, "c":-1.24609254446993, "minSinkSpeed":78, "minSinkRate":0.441069035119},
  {"glider":"Nimbus 4DM" , "glider_and_max_pilot_wgt":820, "max_ballast":168, "V1":100.01,"W1":-0.48, "V2":150.01, "W2":-0.87, "V3":190.76, "W3":-1.6, "wing_area":17.8, "ballast_dump_time":50, "handicap":123, "glider_empty_mass":595, "pilotMass":225, "a":-0.000111450252666092, "b":0.0200647921715763, "c":-1.37195442676807, "minSinkSpeed":90, "minSinkRate":0.433877986578093},
  {"glider":"Nimbus 4D" , "glider_and_max_pilot_wgt":743, "max_ballast":303, "V1":107.5,"W1":-0.5, "V2":142.74, "W2":-0.83, "V3":181.51, "W3":-1.6, "wing_area":17.8, "ballast_dump_time":50, "handicap":123, "glider_empty_mass":515, "pilotMass":228, "a":-0.00014182351528105, "b":0.0261255577806154, "c":-1.66954946294953, "minSinkSpeed":92, "minSinkRate":0.734003703346763},
  {"glider":"Para Competition" , "glider_and_max_pilot_wgt":100, "max_ballast":0, "V1":39,"W1":-1, "V2":45, "W2":-1.1, "V3":64, "W3":-2.3, "wing_area":0, "ballast_dump_time":0, "handicap":0, "glider_empty_mass":0, "pilotMass":100, "a":-0.00185964912280702, "b":0.139543859649123, "c":-3.61368421052631, "minSinkSpeed":38, "minSinkRate":1.68911387134503},
  {"glider":"Para EN A/DHV1" , "glider_and_max_pilot_wgt":100, "max_ballast":0, "V1":29,"W1":-1.1, "V2":34, "W2":-1.3, "V3":44, "W3":-2.3, "wing_area":0, "ballast_dump_time":0, "handicap":0, "glider_empty_mass":0, "pilotMass":100, "a":-0.004, "b":0.212, "c":-3.884, "minSinkSpeed":27, "minSinkRate":1.840432},
  {"glider":"Para EN B/DHV12" , "glider_and_max_pilot_wgt":100, "max_ballast":0, "V1":29.5,"W1":-1.1, "V2":37, "W2":-1.2, "V3":50, "W3":-2.3, "wing_area":0, "ballast_dump_time":0, "handicap":0, "glider_empty_mass":0, "pilotMass":100, "a":-0.00347717323327079, "b":0.217898686679175, "c":-4.50200125078174, "minSinkSpeed":31, "minSinkRate":2.25323284901719},
  {"glider":"Para EN C/DHV2" , "glider_and_max_pilot_wgt":110, "max_ballast":4.19, "V1":33,"W1":-1, "V2":39, "W2":-1.2, "V3":56, "W3":-2.3, "wing_area":0, "ballast_dump_time":0, "handicap":0, "glider_empty_mass":0, "pilotMass":110, "a":-0.00136402387041773, "b":0.0648763853367434, "c":-1.65549872122762, "minSinkSpeed":24, "minSinkRate":-0.0984208196789223},
  {"glider":"Para EN D/DHV23" , "glider_and_max_pilot_wgt":100, "max_ballast":0, "V1":33,"W1":-1.1, "V2":41, "W2":-1.2, "V3":58, "W3":-2.3, "wing_area":0, "ballast_dump_time":0, "handicap":0, "glider_empty_mass":0, "pilotMass":100, "a":-0.00208823529411765, "b":0.142029411764706, "c":-3.51288235294118, "minSinkSpeed":34, "minSinkRate":1.31626591176471},
  {"glider":"Pegase 101A" , "glider_and_max_pilot_wgt":344, "max_ballast":120, "V1":85,"W1":-0.62, "V2":105, "W2":-0.75, "V3":175, "W3":-2.54, "wing_area":10.5, "ballast_dump_time":0, "handicap":102, "glider_empty_mass":252, "pilotMass":92, "a":-0.000211904761904762, "b":0.0337619047619047, "c":-1.95875, "minSinkSpeed":80, "minSinkRate":0.74220597324263},
  {"glider":"Phoebus C" , "glider_and_max_pilot_wgt":310, "max_ballast":150, "V1":100,"W1":-0.7, "V2":120, "W2":-0.98, "V3":150, "W3":-1.58, "wing_area":14.06, "ballast_dump_time":0, "handicap":100, "glider_empty_mass":225, "pilotMass":85, "a":-0.00012, "b":0.0124, "c":-0.74, "minSinkSpeed":52, "minSinkRate":-0.0951992511999996},
  {"glider":"PIK-20B" , "glider_and_max_pilot_wgt":354, "max_ballast":144, "V1":102.5,"W1":-0.69, "V2":157.76, "W2":-1.59, "V3":216.91, "W3":-3.6, "wing_area":10, "ballast_dump_time":0, "handicap":102, "glider_empty_mass":240, "pilotMass":114, "a":-0.000154660941010684, "b":0.0239654115563005, "c":-1.52154817302731, "minSinkSpeed":77, "minSinkRate":0.323790358648348},
  {"glider":"PIK-20D" , "glider_and_max_pilot_wgt":348, "max_ballast":144, "V1":100,"W1":-0.69, "V2":156.54, "W2":-1.78, "V3":215.24, "W3":-4.2, "wing_area":10, "ballast_dump_time":0, "handicap":104, "glider_empty_mass":227, "pilotMass":121, "a":-0.000190456341778308, "b":0.0295812829371399, "c":-1.74356487593092, "minSinkSpeed":78, "minSinkRate":0.563778022508209},
  {"glider":"PIK-20E" , "glider_and_max_pilot_wgt":437, "max_ballast":80, "V1":109.61,"W1":-0.83, "V2":166.68, "W2":-2, "V3":241.15, "W3":-4.7, "wing_area":10, "ballast_dump_time":0, "handicap":104, "glider_empty_mass":324, "pilotMass":113, "a":-0.000119773997281601, "b":0.0125912187567695, "c":-0.771116512163913, "minSinkSpeed":53, "minSinkRate":-0.103781157727176},
  {"glider":"PIK-30M" , "glider_and_max_pilot_wgt":460, "max_ballast":0, "V1":123.6,"W1":-0.78, "V2":152.04, "W2":-1.12, "V3":200.22, "W3":-2.2, "wing_area":10.63, "ballast_dump_time":0, "handicap":0, "glider_empty_mass":347, "pilotMass":113, "a":-0.000136530243493973, "b":0.0256782033490274, "c":-1.86805886529211, "minSinkSpeed":94, "minSinkRate":0.545694001724164},
  {"glider":"Pilatus B4 FG" , "glider_and_max_pilot_wgt":306, "max_ballast":0, "V1":90,"W1":-0.847, "V2":126, "W2":-1.644, "V3":198, "W3":-5.098, "wing_area":14, "ballast_dump_time":0, "handicap":86, "glider_empty_mass":230, "pilotMass":76, "a":-0.000239197530864198, "b":0.0295277777777778, "c":-1.56700000000001, "minSinkSpeed":62, "minSinkRate":0.263725769580663},
  {"glider":"PW-5 Smyk" , "glider_and_max_pilot_wgt":300, "max_ballast":0, "V1":99.5,"W1":-0.95, "V2":158.48, "W2":-2.85, "V3":198.1, "W3":-5.1, "wing_area":10.16, "ballast_dump_time":0, "handicap":85, "glider_empty_mass":190, "pilotMass":110, "a":-0.000249241281103716, "b":0.0320849557635652, "c":-1.67490210522768, "minSinkSpeed":64, "minSinkRate":0.378539039398333},
  {"glider":"PW-6" , "glider_and_max_pilot_wgt":546, "max_ballast":0, "V1":104,"W1":-0.847, "V2":152, "W2":-1.994, "V3":200, "W3":-4.648, "wing_area":15.3, "ballast_dump_time":0, "handicap":86, "glider_empty_mass":360, "pilotMass":186, "a":-0.000327039930555556, "b":0.0598263888888889, "c":-3.53168055555556, "minSinkSpeed":91, "minSinkRate":1.91253056624891},
  {"glider":"R-26S Gobe" , "glider_and_max_pilot_wgt":420, "max_ballast":0, "V1":60,"W1":-1.02, "V2":80, "W2":-0.96, "V3":120, "W3":-2.11, "wing_area":18, "ballast_dump_time":30.5, "handicap":0, "glider_empty_mass":230, "pilotMass":190, "a":-0.000529166666666667, "b":0.0770833333333334, "c":-3.74, "minSinkSpeed":73, "minSinkRate":1.8871037746007},
  {"glider":"Russia AC-4" , "glider_and_max_pilot_wgt":250, "max_ballast":0, "V1":99.3,"W1":-0.92, "V2":140.01, "W2":-1.8, "V3":170.01, "W3":-2.9, "wing_area":7.7, "ballast_dump_time":0, "handicap":84, "glider_empty_mass":140, "pilotMass":110, "a":-0.000212846219457549, "b":0.0293199182895626, "c":-1.7326998676546, "minSinkSpeed":69, "minSinkRate":0.290377620267624},
  {"glider":"SF-27B" , "glider_and_max_pilot_wgt":300, "max_ballast":0, "V1":100,"W1":-0.81, "V2":120, "W2":-1.27, "V3":150, "W3":-2.5, "wing_area":13, "ballast_dump_time":0, "handicap":88, "glider_empty_mass":220, "pilotMass":80, "a":-0.00036, "b":0.0562, "c":-2.83, "minSinkSpeed":78, "minSinkRate":1.5536101088},
  {"glider":"SGS 1-26E" , "glider_and_max_pilot_wgt":315, "max_ballast":0, "V1":82.3,"W1":-1.04, "V2":117.73, "W2":-1.88, "V3":156.86, "W3":-3.8, "wing_area":14.87, "ballast_dump_time":0, "handicap":63, "glider_empty_mass":202, "pilotMass":113, "a":-0.000340108509058292, "b":0.0443231836444069, "c":-2.38414445061525, "minSinkSpeed":65, "minSinkRate":0.496870005068065},
  {"glider":"SGS 1-34" , "glider_and_max_pilot_wgt":354, "max_ballast":0, "V1":89.82,"W1":-0.8, "V2":143.71, "W2":-2.1, "V3":179.64, "W3":-3.8, "wing_area":14.03, "ballast_dump_time":0, "handicap":85, "glider_empty_mass":259, "pilotMass":95, "a":-0.000258194256782158, "b":0.036172890831986, "c":-1.96603270301932, "minSinkSpeed":70, "minSinkRate":0.566074321718896},
  {"glider":"SGS 1-35A" , "glider_and_max_pilot_wgt":381, "max_ballast":179, "V1":98.68,"W1":-0.74, "V2":151.82, "W2":-1.8, "V3":202.87, "W3":-3.9, "wing_area":9.64, "ballast_dump_time":0, "handicap":0, "glider_empty_mass":180, "pilotMass":201, "a":-0.000203367233353398, "b":0.030996182959919, "c":-1.81836560348873, "minSinkSpeed":76, "minSinkRate":0.537347444690717},
  {"glider":"SGS 1-36 Sprite" , "glider_and_max_pilot_wgt":322, "max_ballast":0, "V1":75.98,"W1":-0.68, "V2":132.96, "W2":-2, "V3":170.95, "W3":-4.1, "wing_area":13.1, "ballast_dump_time":0, "handicap":76, "glider_empty_mass":215, "pilotMass":107, "a":-0.000338124476077685, "b":0.0474817048656483, "c":-2.33568072502473, "minSinkSpeed":70, "minSinkRate":0.988046618541937},
  {"glider":"SGS 2-33" , "glider_and_max_pilot_wgt":470, "max_ballast":0, "V1":82.32,"W1":-0.96, "V2":130, "W2":-1.74, "V3":170, "W3":-3.44, "wing_area":20.35, "ballast_dump_time":33, "handicap":54, "glider_empty_mass":272, "pilotMass":198, "a":-0.000298140278254053, "b":0.046942083476216, "c":-2.80390014941458, "minSinkSpeed":79, "minSinkRate":0.904531467328902},
  {"glider":"Silene E78" , "glider_and_max_pilot_wgt":450, "max_ballast":0, "V1":75,"W1":-0.548, "V2":125, "W2":-1.267, "V3":160, "W3":-2.439, "wing_area":18, "ballast_dump_time":47.222, "handicap":0, "glider_empty_mass":365, "pilotMass":85, "a":-0.000224773109243698, "b":0.0305746218487395, "c":-1.57674789915967, "minSinkSpeed":68, "minSinkRate":0.502329822115265},
  {"glider":"Skylark 4" , "glider_and_max_pilot_wgt":395, "max_ballast":0, "V1":78,"W1":-0.637, "V2":139, "W2":-2, "V3":200, "W3":-5.092, "wing_area":16.1, "ballast_dump_time":0, "handicap":84, "glider_empty_mass":258, "pilotMass":137, "a":-0.000232330018812147, "b":0.028071351787154, "c":-1.41306960494491, "minSinkSpeed":60, "minSinkRate":0.271214740918591},
  {"glider":"Std Austria S" , "glider_and_max_pilot_wgt":297, "max_ballast":0, "V1":70,"W1":-0.7, "V2":118, "W2":-1, "V3":145, "W3":-1.5, "wing_area":13.5, "ballast_dump_time":38.9, "handicap":90, "glider_empty_mass":205, "pilotMass":92, "a":-0.00016358024691358, "b":0.0245030864197531, "c":-1.61367283950617, "minSinkSpeed":75, "minSinkRate":0.224060648862598},
  {"glider":"Std Cirrus" , "glider_and_max_pilot_wgt":337, "max_ballast":80, "V1":93.23,"W1":-0.74, "V2":149.17, "W2":-1.71, "V3":205.1, "W3":-4.2, "wing_area":10.04, "ballast_dump_time":0, "handicap":99, "glider_empty_mass":215, "pilotMass":122, "a":-0.000242959939959861, "b":0.0415534822957519, "c":-2.50226395490781, "minSinkSpeed":86, "minSinkRate":1.07134059906665},
  {"glider":"Stemme S-10" , "glider_and_max_pilot_wgt":850, "max_ballast":0, "V1":133.47,"W1":-0.83, "V2":167.75, "W2":-1.41, "V3":205.03, "W3":-2.3, "wing_area":18.7, "ballast_dump_time":0, "handicap":110, "glider_empty_mass":645, "pilotMass":205, "a":-0.0000971758521079243, "b":0.0123518235908521, "c":-0.747483855557694, "minSinkSpeed":64, "minSinkRate":0.0430334586181999},
  {"glider":"SZD-30 Pirat" , "glider_and_max_pilot_wgt":370, "max_ballast":0, "V1":80,"W1":-0.72, "V2":100, "W2":-0.98, "V3":150, "W3":-2.46, "wing_area":13.8, "ballast_dump_time":0, "handicap":86, "glider_empty_mass":260, "pilotMass":110, "a":-0.000237142857142857, "b":0.0296857142857143, "c":-1.57714285714286, "minSinkSpeed":63, "minSinkRate":0.293060685771429},
  {"glider":"SZD-36 Cobra" , "glider_and_max_pilot_wgt":350, "max_ballast":30, "V1":70.8,"W1":-0.6, "V2":94.5, "W2":-0.69, "V3":148.1, "W3":-1.83, "wing_area":11.6, "ballast_dump_time":0, "handicap":98, "glider_empty_mass":275, "pilotMass":75, "a":-0.000226017960698416, "b":0.0335633005490177, "c":-1.84333500835515, "minSinkSpeed":74, "minSinkRate":0.640353012496937},
  {"glider":"SZD-42 Jantar II" , "glider_and_max_pilot_wgt":482, "max_ballast":191, "V1":109.5,"W1":-0.66, "V2":157.14, "W2":-1.47, "V3":196.42, "W3":-2.7, "wing_area":14.27, "ballast_dump_time":0, "handicap":113, "glider_empty_mass":362, "pilotMass":120, "a":-0.00016464710917503, "b":0.0268989862987423, "c":-1.63127899892638, "minSinkSpeed":82, "minSinkRate":0.574440100481476},
  {"glider":"SZD-48-2 Jantar Std 2" , "glider_and_max_pilot_wgt":375, "max_ballast":150, "V1":100,"W1":-0.73, "V2":120, "W2":-0.95, "V3":150, "W3":-1.6, "wing_area":10.66, "ballast_dump_time":0, "handicap":100, "glider_empty_mass":274, "pilotMass":101, "a":-0.000213333333333334, "b":0.0359333333333334, "c":-2.19, "minSinkSpeed":84, "minSinkRate":0.828403822933335},
  {"glider":"SZD-48-3 Jantar Std 3" , "glider_and_max_pilot_wgt":326, "max_ballast":150, "V1":95,"W1":-0.66, "V2":180, "W2":-2.24, "V3":220, "W3":-3.85, "wing_area":10.66, "ballast_dump_time":0, "handicap":100, "glider_empty_mass":274, "pilotMass":52, "a":-0.000173294117647059, "b":0.0290676470588235, "c":-1.85744705882353, "minSinkSpeed":84, "minSinkRate":0.584237816709149},
  {"glider":"SZD-50 Puchacz" , "glider_and_max_pilot_wgt":435, "max_ballast":135, "V1":100,"W1":-1, "V2":120, "W2":-1.42, "V3":150, "W3":-2.35, "wing_area":18.16, "ballast_dump_time":0, "handicap":84, "glider_empty_mass":370, "pilotMass":65, "a":-0.0002, "b":0.0230000000000001, "c":-1.3, "minSinkSpeed":58, "minSinkRate":0.0340023199999999},
  {"glider":"SZD-51-1 Junior" , "glider_and_max_pilot_wgt":333, "max_ballast":0, "V1":70,"W1":-0.58, "V2":130, "W2":-1.6, "V3":180, "W3":-3.6, "wing_area":12.51, "ballast_dump_time":0, "handicap":90, "glider_empty_mass":242, "pilotMass":91, "a":-0.000209090909090909, "b":0.0248181818181818, "c":-1.29272727272727, "minSinkSpeed":59, "minSinkRate":0.171548033966942},
  {"glider":"SZD-54-2 Perkoz (FT 17m) /* flat tip */" , "glider_and_max_pilot_wgt":442, "max_ballast":0, "V1":98,"W1":-0.92, "V2":174, "W2":-4.35, "V3":250, "W3":-13.22, "wing_area":16.36, "ballast_dump_time":47.05, "handicap":98, "glider_empty_mass":375, "pilotMass":67, "a":-0.000470914127423823, "b":0.0829570637119114, "c":-4.52713296398893, "minSinkSpeed":88, "minSinkRate":2.77310815754943},
  {"glider":"SZD-54-2 Perkoz (WL 17m) /* winglet */" , "glider_and_max_pilot_wgt":442, "max_ballast":0, "V1":99,"W1":-0.86, "V2":175, "W2":-4.22, "V3":250, "W3":-13.01, "wing_area":16.36, "ballast_dump_time":47.05, "handicap":98, "glider_empty_mass":375, "pilotMass":67, "a":-0.000483373997908679, "b":0.0882339491111886, "c":-4.85761240850471, "minSinkSpeed":91, "minSinkRate":3.17169822280184},
  {"glider":"SZD-54-2 Perkoz (WL 20m) /* long winglet */" , "glider_and_max_pilot_wgt":442, "max_ballast":0, "V1":91,"W1":-0.69, "V2":170, "W2":-3.98, "V3":250, "W3":-12.66, "wing_area":17.3, "ballast_dump_time":47.05, "handicap":102, "glider_empty_mass":380, "pilotMass":62, "a":-0.000420468115595892, "b":0.0680966085502746, "c":-3.40489491282541, "minSinkSpeed":81, "minSinkRate":2.11094470001517},
  {"glider":"SZD-55-1 Promyk" , "glider_and_max_pilot_wgt":350, "max_ballast":200, "V1":100,"W1":-0.66, "V2":120, "W2":-0.86, "V3":150, "W3":-1.4, "wing_area":9.6, "ballast_dump_time":0, "handicap":106, "glider_empty_mass":215, "pilotMass":135, "a":-0.00016, "b":0.0252, "c":-1.58, "minSinkSpeed":79, "minSinkRate":0.4108020224},
  {"glider":"SZD-9 bis 1E Bocian" , "glider_and_max_pilot_wgt":540, "max_ballast":0, "V1":70,"W1":-0.83, "V2":90, "W2":-1, "V3":140, "W3":-2.53, "wing_area":20, "ballast_dump_time":0, "handicap":76, "glider_empty_mass":330, "pilotMass":210, "a":-0.000315714285714286, "b":0.0420142857142857, "c":-2.224, "minSinkSpeed":67, "minSinkRate":0.590963821116327},
  {"glider":"Taurus" , "glider_and_max_pilot_wgt":472, "max_ballast":0, "V1":100,"W1":-0.71, "V2":120, "W2":-0.83, "V3":150, "W3":-1.35, "wing_area":12.26, "ballast_dump_time":0, "handicap":99, "glider_empty_mass":306, "pilotMass":166, "a":-0.000226666666666667, "b":0.0438666666666667, "c":-2.83, "minSinkSpeed":97, "minSinkRate":1.42507165031111},
  {"glider":"Ventus 2c (18m)" , "glider_and_max_pilot_wgt":385, "max_ballast":180, "V1":80,"W1":-0.5, "V2":120, "W2":-0.73, "V3":180, "W3":-2, "wing_area":11.03, "ballast_dump_time":55.555, "handicap":120, "glider_empty_mass":260, "pilotMass":125, "a":-0.000154166666666667, "b":0.0250833333333333, "c":-1.52, "minSinkSpeed":81, "minSinkRate":0.511751925156249},
  {"glider":"Ventus 2cT (18m)" , "glider_and_max_pilot_wgt":410, "max_ballast":110, "V1":100,"W1":-0.62, "V2":150, "W2":-1.2, "V3":200, "W3":-2.3, "wing_area":11.03, "ballast_dump_time":55.555, "handicap":120, "glider_empty_mass":305, "pilotMass":105, "a":-0.000104, "b":0.0144, "c":-1.02, "minSinkSpeed":69, "minSinkRate":-0.0263992536959996},
  {"glider":"Ventus 2cx (18m)" , "glider_and_max_pilot_wgt":385, "max_ballast":215, "V1":80,"W1":-0.5, "V2":120, "W2":-0.73, "V3":180, "W3":-2, "wing_area":11.03, "ballast_dump_time":55.555, "handicap":120, "glider_empty_mass":265, "pilotMass":120, "a":-0.000154166666666667, "b":0.0250833333333333, "c":-1.52, "minSinkSpeed":81, "minSinkRate":0.511751925156249},
  {"glider":"Ventus 2cxT (18m)" , "glider_and_max_pilot_wgt":470, "max_ballast":130, "V1":100,"W1":-0.56, "V2":150, "W2":-1.13, "V3":200, "W3":-2.28, "wing_area":11.03, "ballast_dump_time":55.555, "handicap":120, "glider_empty_mass":310, "pilotMass":160, "a":-0.000116, "b":0.0176, "c":-1.16, "minSinkSpeed":76, "minSinkRate":0.177601022656},
  {"glider":"Ventus a/b (16.6m)" , "glider_and_max_pilot_wgt":358, "max_ballast":151, "V1":100.17,"W1":-0.64, "V2":159.69, "W2":-1.47, "V3":239.54, "W3":-4.3, "wing_area":9.96, "ballast_dump_time":55.555, "handicap":113, "glider_empty_mass":250, "pilotMass":108, "a":-0.000154240943178151, "b":0.0261361590211562, "c":-1.71040096773638, "minSinkSpeed":85, "minSinkRate":0.511174571234717},
  {"glider":"Ventus b (15m)" , "glider_and_max_pilot_wgt":341, "max_ballast":151, "V1":97.69,"W1":-0.68, "V2":156.3, "W2":-1.46, "V3":234.45, "W3":-3.9, "wing_area":9.51, "ballast_dump_time":55.555, "handicap":110, "glider_empty_mass":240, "pilotMass":101, "a":-0.000130986398032134, "b":0.0199609260739228, "c":-1.37993564721248, "minSinkSpeed":76, "minSinkRate":0.137096038370825},
  {"glider":"Ventus cM (17.6)" , "glider_and_max_pilot_wgt":430, "max_ballast":0, "V1":100.17,"W1":-0.6, "V2":159.7, "W2":-1.32, "V3":210.54, "W3":-2.5, "wing_area":10.14, "ballast_dump_time":55.555, "handicap":115, "glider_empty_mass":360, "pilotMass":70, "a":-0.000100709691615192, "b":0.0140766854132233, "c":-0.999537621665646, "minSinkSpeed":70, "minSinkRate":-0.0141689327690794},
  {"glider":"VSO-10 Gradient" , "glider_and_max_pilot_wgt":347, "max_ballast":0, "V1":90,"W1":-0.78, "V2":130, "W2":-1.41, "V3":160, "W3":-2.44, "wing_area":12, "ballast_dump_time":44.444, "handicap":96, "glider_empty_mass":250, "pilotMass":97, "a":-0.000265476190476191, "b":0.0426547619047619, "c":-2.46857142857143, "minSinkSpeed":80, "minSinkRate":0.943815162018141},
  {"glider":"VT-116 Orlik II" , "glider_and_max_pilot_wgt":335, "max_ballast":0, "V1":80,"W1":-0.7, "V2":100, "W2":-1.05, "V3":120, "W3":-1.65, "wing_area":12.8, "ballast_dump_time":33.333, "handicap":86, "glider_empty_mass":215, "pilotMass":120, "a":-0.0003125, "b":0.0387499999999999, "c":-1.8, "minSinkSpeed":62, "minSinkRate":0.602506054687499},
  {"glider":"WA 26 P Squale" , "glider_and_max_pilot_wgt":330, "max_ballast":0, "V1":80,"W1":-0.61, "V2":152, "W2":-2, "V3":174, "W3":-3, "wing_area":12.6, "ballast_dump_time":0, "handicap":86, "glider_empty_mass":228, "pilotMass":102, "a":-0.000278180743606276, "b":0.0452323769611004, "c":-2.44823339780787, "minSinkSpeed":81, "minSinkRate":1.21559540418788},
  {"glider":"Zuni II" , "glider_and_max_pilot_wgt":358, "max_ballast":182, "V1":110,"W1":-0.88, "V2":167, "W2":-2.21, "V3":203.72, "W3":-3.6, "wing_area":10.13, "ballast_dump_time":0, "handicap":0, "glider_empty_mass":238, "pilotMass":120, "a":-0.00015493701630128, "b":0.0195842201821213, "c":-1.15952632278785, "minSinkSpeed":63, "minSinkRate":0.0742810610309683}
]}